<points>
    <group value='ql'>
        <point value='ql_dzb'>
            <pos x='694' y='487' r='20' g='18' b='18'/>
            <pos x='754' y='487' r='20' g='18' b='18'/>
            <pos x='864' y='487' r='121' g='121' b='121'/>
        </point>
        <point value='ql_zb_1'>
            <pos x='694' y='487' r='255' g='255' b='255'/>
            <pos x='754' y='487' r='255' g='255' b='255'/>
            <pos x='864' y='487' r='255' g='255' b='255'/>
        </point>
        <point value='ql_zb_2'>
            <pos x='694' y='487' r='3' g='3' b='3'/>
            <pos x='754' y='487' r='3' g='3' b='3'/>
            <pos x='864' y='487' r='3' g='3' b='3'/>
        </point>
        <point value='ql_f10'>
            <pos x='1372' y='67' r='32' g='15' b='17'/>
            <pos x='1392' y='67' r='176' g='149' b='102'/>
            <pos x='1413' y='67' r='121' g='98' b='69'/>
        </point>
        <point value='ql_over'>
            <pos x='1' y='5' r='3' g='3' b='3'/>
            <pos x='2' y='6' r='3' g='3' b='3'/>
            <pos x='3' y='7' r='3' g='3' b='3'/>
        </point>
        <point value='ql_qr'>
            <pos x='790' y='503' r='17' g='69' b='129'/>
            <pos x='815' y='503' r='17' g='69' b='129'/>
            <pos x='835' y='503' r='17' g='69' b='129'/>
        </point>
        <point value='ql_door'>
            <pos x='694' y='487' r='88' g='55' b='32'/>
            <pos x='754' y='487' r='145' g='118' b='86'/>
            <pos x='864' y='487' r='85' g='65' b='52'/>
        </point>
        <point value='ql_skill'>
            <pos x='912' y='822' r='27' g='3' b='3'/>
            <pos x='922' y='822' r='28' g='4' b='4'/>
            <pos x='932' y='822' r='26' g='5' b='5'/>
        </point>
    </group>
</points>